baste/__init__.py
baste/py24.py
baste-0.1.0.dist-info/LICENSE
baste-0.1.0.dist-info/WHEEL
baste-0.1.0.dist-info/METADATA
baste-0.1.0.dist-info/RECORD
